hypopt/__init__.py
hypopt/model_selection.py
hypopt/version.py
hypopt-1.0.9.dist-info/DESCRIPTION.rst
hypopt-1.0.9.dist-info/METADATA
hypopt-1.0.9.dist-info/RECORD
hypopt-1.0.9.dist-info/WHEEL
hypopt-1.0.9.dist-info/metadata.json
hypopt-1.0.9.dist-info/top_level.txt
