Metadata-Version: 1.1
Name: hypopt
Version: 1.0.9
Summary: Grid search hyper-parameter optimization using a validation set (not cross validation)
Home-page: https://github.com/cgnorthcutt/hypopt
Author: Curtis G. Northcutt
Author-email: cgn@mit.edu
License: MIT
Keywords: machine_learning classification regression hyper-parameter-optimization parameter optimization scikit-learn machine learning cross-validation validation
Platform: UNKNOWN
Classifier: Development Status :: 3 - Alpha
Classifier: Intended Audience :: Developers
Classifier: Topic :: Software Development :: Libraries :: Python Modules
Classifier: License :: OSI Approved :: MIT License
Classifier: Programming Language :: Python :: 2.7
Classifier: Programming Language :: Python :: 3.4
Classifier: Programming Language :: Python :: 3.5
Classifier: Programming Language :: Python :: 3.6
